_npysearch.cp310-win_amd64.pyd
npysearch/__init__.py
npysearch-1.3.1.dist-info/LICENSE
npysearch-1.3.1.dist-info/METADATA
npysearch-1.3.1.dist-info/WHEEL
npysearch-1.3.1.dist-info/top_level.txt
npysearch-1.3.1.dist-info/RECORD
