Metadata-Version: 2.1
Name: npysearch
Version: 1.3.1
Summary: Python bindings for nsearch, an efficient BLAST-like sequence comparison algorithm written in C++
Home-page: https://github.com/jeevannavar/npysearch
Author: Aditya Jeevannavar
Author-email: adjeev@utu.fi
Keywords: BLAST nsearch bioinformatics
Classifier: Development Status :: 5 - Production/Stable
Classifier: Intended Audience :: Science/Research
Classifier: Topic :: Scientific/Engineering :: Bio-Informatics
Classifier: License :: OSI Approved :: BSD License
Classifier: Programming Language :: Python
Classifier: Programming Language :: Python :: 3
Classifier: Programming Language :: Python :: 3.10
Requires-Python: >=3.6
License-File: LICENSE
Provides-Extra: test
Requires-Dist: pytest ; extra == 'test'
